{
    "CALIB short Arcs all": {
        "wavelength": {
            "B": [
                4048.0,
                4679.0,
                4801.0,
                5087.0,
                5462.0
            ],
            "R": [
                6145.0,
                6385.0,
                6404.0,
                6508.0,
                6680.0,
                6931.0,
                7034.0,
                7247.0
            ],
            "Z": [
                7604.0,
                8115.0,
                8192.0,
                8266.0,
                8301.0,
                8779.0,
                8822.0,
                8931.0
            ]
        },
        "area": {
            "spectrograph": {
                "settings": {
                    "fiberlo": 240,
                    "fiberhi": 260,
                    "npix": 12,
                    "comment": "Fiber range used in spectrum; number of pixels used around line center."
                },
                "0": {
                    "B": {
                        "upper_err": [
                            16546.56,
                            7559.04,
                            18591.32,
                            24578.04,
                            54643.08
                        ],
                        "upper": [
                            14945.28,
                            6827.52,
                            16792.16,
                            22199.52,
                            49355.04000000001
                        ],
                        "nominal": [
                            13344.0,
                            6096.0,
                            14993.0,
                            19821.0,
                            44067.0
                        ],
                        "lower": [
                            11742.72,
                            5364.4800000000005,
                            13193.84,
                            17442.48,
                            38778.96
                        ],
                        "lower_err": [
                            10141.44,
                            4632.96,
                            11394.68,
                            15063.960000000001,
                            33490.92
                        ]
                    },
                    "R": {
                        "upper_err": [
                            31333.56,
                            35712.0,
                            68740.64,
                            38599.96,
                            32630.6,
                            33032.36,
                            129824.28,
                            58661.92
                        ],
                        "upper": [
                            28301.280000000002,
                            32256.000000000004,
                            62088.32000000001,
                            34864.48,
                            29472.800000000003,
                            29835.680000000004,
                            117260.64000000001,
                            52984.96000000001
                        ],
                        "nominal": [
                            25269.0,
                            28800.0,
                            55436.0,
                            31129.0,
                            26315.0,
                            26639.0,
                            104697.0,
                            47308.0
                        ],
                        "lower": [
                            22236.72,
                            25344.0,
                            48783.68,
                            27393.52,
                            23157.2,
                            23442.32,
                            92133.36,
                            41631.04
                        ],
                        "lower_err": [
                            19204.44,
                            21888.0,
                            42131.36,
                            23658.04,
                            19999.4,
                            20245.64,
                            79569.72,
                            35954.08
                        ]
                    },
                    "Z": {
                        "upper_err": [
                            48763.0,
                            122583.92,
                            34302.12,
                            32262.32,
                            63197.84,
                            72346.56,
                            38311.04,
                            50489.08
                        ],
                        "upper": [
                            44044.00000000001,
                            110720.96,
                            30982.56,
                            29140.160000000003,
                            57081.920000000006,
                            65345.280000000006,
                            34603.520000000004,
                            45603.04
                        ],
                        "nominal": [
                            39325.0,
                            98858.0,
                            27663.0,
                            26018.0,
                            50966.0,
                            58344.0,
                            30896.0,
                            40717.0
                        ],
                        "lower": [
                            34606.0,
                            86995.04,
                            24343.44,
                            22895.84,
                            44850.08,
                            51342.72,
                            27188.48,
                            35830.96
                        ],
                        "lower_err": [
                            29887.0,
                            75132.08,
                            21023.88,
                            19773.68,
                            38734.16,
                            44341.44,
                            23480.96,
                            30944.920000000002
                        ]
                    }
                },
                "1": {
                    "B": {
                        "upper_err": [
                            16723.88,
                            8210.039999999999,
                            20571.6,
                            28688.64,
                            69452.4
                        ],
                        "upper": [
                            15105.440000000002,
                            7415.52,
                            18580.800000000003,
                            25912.320000000003,
                            62731.200000000004
                        ],
                        "nominal": [
                            13487.0,
                            6621.0,
                            16590.0,
                            23136.0,
                            56010.0
                        ],
                        "lower": [
                            11868.56,
                            5826.4800000000005,
                            14599.2,
                            20359.68,
                            49288.8
                        ],
                        "lower_err": [
                            10250.12,
                            5031.96,
                            12608.4,
                            17583.36,
                            42567.6
                        ]
                    },
                    "R": {
                        "upper_err": [
                            31802.28,
                            36184.44,
                            69996.76,
                            38931.04,
                            33439.08,
                            33811.08,
                            133471.12,
                            61181.6
                        ],
                        "upper": [
                            28724.640000000003,
                            32682.720000000005,
                            63222.880000000005,
                            35163.520000000004,
                            30203.040000000005,
                            30539.040000000005,
                            120554.56000000001,
                            55260.8
                        ],
                        "nominal": [
                            25647.0,
                            29181.0,
                            56449.0,
                            31396.0,
                            26967.0,
                            27267.0,
                            107638.0,
                            49340.0
                        ],
                        "lower": [
                            22569.36,
                            25679.28,
                            49675.12,
                            27628.48,
                            23730.96,
                            23994.96,
                            94721.44,
                            43419.2
                        ],
                        "lower_err": [
                            19491.72,
                            22177.56,
                            42901.24,
                            23860.96,
                            20494.920000000002,
                            20722.920000000002,
                            81804.88,
                            37498.4
                        ]
                    },
                    "Z": {
                        "upper_err": [
                            72370.12,
                            130836.12,
                            36881.32,
                            34013.2,
                            67706.48,
                            76624.56,
                            41334.159999999996,
                            54066.48
                        ],
                        "upper": [
                            65366.560000000005,
                            118174.56000000001,
                            33312.16,
                            30721.600000000002,
                            61154.240000000005,
                            69209.28000000001,
                            37334.08,
                            48834.240000000005
                        ],
                        "nominal": [
                            58363.0,
                            105513.0,
                            29743.0,
                            27430.0,
                            54602.0,
                            61794.0,
                            33334.0,
                            43602.0
                        ],
                        "lower": [
                            51359.44,
                            92851.44,
                            26173.84,
                            24138.4,
                            48049.76,
                            54378.72,
                            29333.920000000002,
                            38369.76
                        ],
                        "lower_err": [
                            44355.88,
                            80189.88,
                            22604.68,
                            20846.8,
                            41497.520000000004,
                            46963.44,
                            25333.84,
                            33137.52
                        ]
                    }
                },
                "2": {
                    "B": {
                        "upper_err": [
                            18008.52,
                            8516.32,
                            21135.8,
                            29566.56,
                            68691.04
                        ],
                        "upper": [
                            16265.760000000002,
                            7692.160000000001,
                            19090.4,
                            26705.280000000002,
                            62043.520000000004
                        ],
                        "nominal": [
                            14523.0,
                            6868.0,
                            17045.0,
                            23844.0,
                            55396.0
                        ],
                        "lower": [
                            12780.24,
                            6043.84,
                            14999.6,
                            20982.72,
                            48748.48
                        ],
                        "lower_err": [
                            11037.48,
                            5219.68,
                            12954.2,
                            18121.44,
                            42100.96
                        ]
                    },
                    "R": {
                        "upper_err": [
                            29688.079999999998,
                            33434.12,
                            64501.08,
                            35798.8,
                            29830.68,
                            29755.04,
                            114804.16,
                            51622.44
                        ],
                        "upper": [
                            26815.04,
                            30198.56,
                            58259.04000000001,
                            32334.4,
                            26943.840000000004,
                            26875.520000000004,
                            103694.08000000002,
                            46626.72
                        ],
                        "nominal": [
                            23942.0,
                            26963.0,
                            52017.0,
                            28870.0,
                            24057.0,
                            23996.0,
                            92584.0,
                            41631.0
                        ],
                        "lower": [
                            21068.96,
                            23727.44,
                            45774.96,
                            25405.6,
                            21170.16,
                            21116.48,
                            81473.92,
                            36635.28
                        ],
                        "lower_err": [
                            18195.920000000002,
                            20491.88,
                            39532.92,
                            21941.2,
                            18283.32,
                            18236.96,
                            70363.84,
                            31639.56
                        ]
                    },
                    "Z": {
                        "upper_err": [
                            84426.64,
                            125440.88,
                            35325.12,
                            33388.24,
                            65042.96,
                            75478.8,
                            41063.84,
                            51943.6
                        ],
                        "upper": [
                            76256.32,
                            113301.44000000002,
                            31906.56,
                            30157.120000000003,
                            58748.48,
                            68174.40000000001,
                            37089.920000000006,
                            46916.8
                        ],
                        "nominal": [
                            68086.0,
                            101162.0,
                            28488.0,
                            26926.0,
                            52454.0,
                            60870.0,
                            33116.0,
                            41890.0
                        ],
                        "lower": [
                            59915.68,
                            89022.56,
                            25069.44,
                            23694.88,
                            46159.52,
                            53565.6,
                            29142.08,
                            36863.2
                        ],
                        "lower_err": [
                            51745.36,
                            76883.12,
                            21650.88,
                            20463.760000000002,
                            39865.04,
                            46261.2,
                            25168.16,
                            31836.4
                        ]
                    }
                },
                "3": {
                    "B": {
                        "upper_err": [
                            16184.48,
                            8502.68,
                            21334.2,
                            29948.48,
                            72304.4
                        ],
                        "upper": [
                            14618.240000000002,
                            7679.840000000001,
                            19269.600000000002,
                            27050.24,
                            65307.200000000004
                        ],
                        "nominal": [
                            13052.0,
                            6857.0,
                            17205.0,
                            24152.0,
                            58310.0
                        ],
                        "lower": [
                            11485.76,
                            6034.16,
                            15140.4,
                            21253.76,
                            51312.8
                        ],
                        "lower_err": [
                            9919.52,
                            5211.32,
                            13075.8,
                            18355.52,
                            44315.6
                        ]
                    },
                    "R": {
                        "upper_err": [
                            28067.4,
                            31660.92,
                            60391.72,
                            33575.48,
                            29352.04,
                            29900.12,
                            115364.64,
                            51631.12
                        ],
                        "upper": [
                            25351.2,
                            28596.960000000003,
                            54547.36000000001,
                            30326.24,
                            26511.520000000004,
                            27006.56,
                            104200.32,
                            46634.560000000005
                        ],
                        "nominal": [
                            22635.0,
                            25533.0,
                            48703.0,
                            27077.0,
                            23671.0,
                            24113.0,
                            93036.0,
                            41638.0
                        ],
                        "lower": [
                            19918.8,
                            22469.04,
                            42858.64,
                            23827.76,
                            20830.48,
                            21219.44,
                            81871.68000000001,
                            36641.44
                        ],
                        "lower_err": [
                            17202.6,
                            19405.08,
                            37014.28,
                            20578.52,
                            17989.96,
                            18325.88,
                            70707.36,
                            31644.88
                        ]
                    },
                    "Z": {
                        "upper_err": [
                            82957.24,
                            126352.28,
                            35599.159999999996,
                            33705.68,
                            65939.48,
                            76723.76,
                            42456.36,
                            53652.32
                        ],
                        "upper": [
                            74929.12000000001,
                            114124.64000000001,
                            32154.08,
                            30443.840000000004,
                            59558.240000000005,
                            69298.88,
                            38347.68,
                            48460.16
                        ],
                        "nominal": [
                            66901.0,
                            101897.0,
                            28709.0,
                            27182.0,
                            53177.0,
                            61874.0,
                            34239.0,
                            43268.0
                        ],
                        "lower": [
                            58872.88,
                            89669.36,
                            25263.920000000002,
                            23920.16,
                            46795.76,
                            54449.12,
                            30130.32,
                            38075.840000000004
                        ],
                        "lower_err": [
                            50844.76,
                            77441.72,
                            21818.84,
                            20658.32,
                            40414.520000000004,
                            47024.24,
                            26021.64,
                            32883.68
                        ]
                    }
                },
                "4": {
                    "B": {
                        "upper_err": [
                            16077.84,
                            9416.56,
                            23592.24,
                            32122.2,
                            82543.08
                        ],
                        "upper": [
                            14521.920000000002,
                            8505.28,
                            21309.120000000003,
                            29013.600000000002,
                            74555.04000000001
                        ],
                        "nominal": [
                            12966.0,
                            7594.0,
                            19026.0,
                            25905.0,
                            66567.0
                        ],
                        "lower": [
                            11410.08,
                            6682.72,
                            16742.88,
                            22796.4,
                            58578.96
                        ],
                        "lower_err": [
                            9854.16,
                            5771.4400000000005,
                            14459.76,
                            19687.8,
                            50590.92
                        ]
                    },
                    "R": {
                        "upper_err": [
                            29540.52,
                            33148.92,
                            63969.12,
                            35712.0,
                            29980.72,
                            29959.64,
                            115979.68,
                            52428.44
                        ],
                        "upper": [
                            26681.760000000002,
                            29940.960000000003,
                            57778.560000000005,
                            32256.000000000004,
                            27079.360000000004,
                            27060.320000000003,
                            104755.84000000001,
                            47354.72
                        ],
                        "nominal": [
                            23823.0,
                            26733.0,
                            51588.0,
                            28800.0,
                            24178.0,
                            24161.0,
                            93532.0,
                            42281.0
                        ],
                        "lower": [
                            20964.24,
                            23525.04,
                            45397.44,
                            25344.0,
                            21276.64,
                            21261.68,
                            82308.16,
                            37207.28
                        ],
                        "lower_err": [
                            18105.48,
                            20317.08,
                            39206.88,
                            21888.0,
                            18375.28,
                            18362.36,
                            71084.32,
                            32133.56
                        ]
                    },
                    "Z": {
                        "upper_err": [
                            41170.48,
                            135287.72,
                            35022.56,
                            32877.36,
                            64599.04,
                            73916.4,
                            40860.48,
                            52132.08
                        ],
                        "upper": [
                            37186.240000000005,
                            122195.36000000002,
                            31633.280000000002,
                            29695.680000000004,
                            58347.520000000004,
                            66763.20000000001,
                            36906.240000000005,
                            47087.04
                        ],
                        "nominal": [
                            33202.0,
                            109103.0,
                            28244.0,
                            26514.0,
                            52096.0,
                            59610.0,
                            32952.0,
                            42042.0
                        ],
                        "lower": [
                            29217.76,
                            96010.64,
                            24854.72,
                            23332.32,
                            45844.48,
                            52456.8,
                            28997.76,
                            36996.96
                        ],
                        "lower_err": [
                            25233.52,
                            82918.28,
                            21465.44,
                            20150.64,
                            39592.96,
                            45303.6,
                            25043.52,
                            31951.920000000002
                        ]
                    }
                },
                "5": {
                    "B": {
                        "upper_err": [
                            15743.039999999999,
                            7864.08,
                            19583.32,
                            27609.84,
                            65743.56
                        ],
                        "upper": [
                            14219.520000000002,
                            7103.040000000001,
                            17688.160000000003,
                            24937.920000000002,
                            59381.280000000006
                        ],
                        "nominal": [
                            12696.0,
                            6342.0,
                            15793.0,
                            22266.0,
                            53019.0
                        ],
                        "lower": [
                            11172.48,
                            5580.96,
                            13897.84,
                            19594.08,
                            46656.72
                        ],
                        "lower_err": [
                            9648.960000000001,
                            4819.92,
                            12002.68,
                            16922.16,
                            40294.44
                        ]
                    },
                    "R": {
                        "upper_err": [
                            25985.44,
                            30208.88,
                            57560.8,
                            32254.88,
                            27345.72,
                            28031.44,
                            107818.0,
                            49375.56
                        ],
                        "upper": [
                            23470.72,
                            27285.440000000002,
                            51990.4,
                            29133.440000000002,
                            24699.36,
                            25318.72,
                            97384.00000000001,
                            44597.280000000006
                        ],
                        "nominal": [
                            20956.0,
                            24362.0,
                            46420.0,
                            26012.0,
                            22053.0,
                            22606.0,
                            86950.0,
                            39819.0
                        ],
                        "lower": [
                            18441.28,
                            21438.56,
                            40849.6,
                            22890.56,
                            19406.64,
                            19893.28,
                            76516.0,
                            35040.72
                        ],
                        "lower_err": [
                            15926.56,
                            18515.12,
                            35279.2,
                            19769.12,
                            16760.28,
                            17180.56,
                            66082.0,
                            30262.44
                        ]
                    },
                    "Z": {
                        "upper_err": [
                            69413.96,
                            114221.36,
                            32944.32,
                            31505.92,
                            61686.28,
                            72425.92,
                            39815.159999999996,
                            51153.72
                        ],
                        "upper": [
                            62696.48,
                            103167.68000000001,
                            29756.160000000003,
                            28456.960000000003,
                            55716.64000000001,
                            65416.96000000001,
                            35962.08,
                            46203.36000000001
                        ],
                        "nominal": [
                            55979.0,
                            92114.0,
                            26568.0,
                            25408.0,
                            49747.0,
                            58408.0,
                            32109.0,
                            41253.0
                        ],
                        "lower": [
                            49261.52,
                            81060.32,
                            23379.84,
                            22359.04,
                            43777.36,
                            51399.04,
                            28255.920000000002,
                            36302.64
                        ],
                        "lower_err": [
                            42544.04,
                            70006.64,
                            20191.68,
                            19310.08,
                            37807.72,
                            44390.08,
                            24402.84,
                            31352.28
                        ]
                    }
                },
                "6": {
                    "B": {
                        "upper_err": [
                            16474.64,
                            7659.48,
                            19796.6,
                            26831.12,
                            61296.92
                        ],
                        "upper": [
                            14880.320000000002,
                            6918.240000000001,
                            17880.800000000003,
                            24234.56,
                            55364.96000000001
                        ],
                        "nominal": [
                            13286.0,
                            6177.0,
                            15965.0,
                            21638.0,
                            49433.0
                        ],
                        "lower": [
                            11691.68,
                            5435.76,
                            14049.2,
                            19041.44,
                            43501.04
                        ],
                        "lower_err": [
                            10097.36,
                            4694.52,
                            12133.4,
                            16444.88,
                            37569.08
                        ]
                    },
                    "R": {
                        "upper_err": [
                            28324.079999999998,
                            32073.84,
                            61899.56,
                            34526.56,
                            29111.48,
                            29875.32,
                            116873.72,
                            53033.56
                        ],
                        "upper": [
                            25583.04,
                            28969.920000000002,
                            55909.280000000006,
                            31185.280000000002,
                            26294.24,
                            26984.160000000003,
                            105563.36000000002,
                            47901.280000000006
                        ],
                        "nominal": [
                            22842.0,
                            25866.0,
                            49919.0,
                            27844.0,
                            23477.0,
                            24093.0,
                            94253.0,
                            42769.0
                        ],
                        "lower": [
                            20100.96,
                            22762.08,
                            43928.72,
                            24502.72,
                            20659.76,
                            21201.84,
                            82942.64,
                            37636.72
                        ],
                        "lower_err": [
                            17359.920000000002,
                            19658.16,
                            37938.44,
                            21161.44,
                            17842.52,
                            18310.68,
                            71632.28,
                            32504.44
                        ]
                    },
                    "Z": {
                        "upper_err": [
                            42417.92,
                            110299.24,
                            31173.6,
                            29224.32,
                            57167.72,
                            66165.16,
                            35015.12,
                            46276.8
                        ],
                        "upper": [
                            38312.96000000001,
                            99625.12000000001,
                            28156.800000000003,
                            26396.160000000003,
                            51635.36000000001,
                            59762.08000000001,
                            31626.56,
                            41798.4
                        ],
                        "nominal": [
                            34208.0,
                            88951.0,
                            25140.0,
                            23568.0,
                            46103.0,
                            53359.0,
                            28238.0,
                            37320.0
                        ],
                        "lower": [
                            30103.04,
                            78276.88,
                            22123.2,
                            20739.84,
                            40570.64,
                            46955.92,
                            24849.44,
                            32841.6
                        ],
                        "lower_err": [
                            25998.08,
                            67602.76,
                            19106.4,
                            17911.68,
                            35038.28,
                            40552.840000000004,
                            21460.88,
                            28363.2
                        ]
                    }
                },
                "7": {
                    "B": {
                        "upper_err": [
                            16509.36,
                            8281.96,
                            20514.56,
                            28474.12,
                            65573.68
                        ],
                        "upper": [
                            14911.680000000002,
                            7480.4800000000005,
                            18529.280000000002,
                            25718.56,
                            59227.840000000004
                        ],
                        "nominal": [
                            13314.0,
                            6679.0,
                            16544.0,
                            22963.0,
                            52882.0
                        ],
                        "lower": [
                            11716.32,
                            5877.52,
                            14558.72,
                            20207.44,
                            46536.16
                        ],
                        "lower_err": [
                            10118.64,
                            5076.04,
                            12573.44,
                            17451.88,
                            40190.32
                        ]
                    },
                    "R": {
                        "upper_err": [
                            27191.96,
                            30771.84,
                            58597.44,
                            33365.92,
                            28294.32,
                            28812.64,
                            111970.76,
                            50610.6
                        ],
                        "upper": [
                            24560.480000000003,
                            27793.920000000002,
                            52926.72000000001,
                            30136.960000000003,
                            25556.160000000003,
                            26024.320000000003,
                            101134.88,
                            45712.8
                        ],
                        "nominal": [
                            21929.0,
                            24816.0,
                            47256.0,
                            26908.0,
                            22818.0,
                            23236.0,
                            90299.0,
                            40815.0
                        ],
                        "lower": [
                            19297.52,
                            21838.08,
                            41585.28,
                            23679.04,
                            20079.84,
                            20447.68,
                            79463.12,
                            35917.2
                        ],
                        "lower_err": [
                            16666.04,
                            18860.16,
                            35914.56,
                            20450.08,
                            17341.68,
                            17659.36,
                            68627.24,
                            31019.4
                        ]
                    },
                    "Z": {
                        "upper_err": [
                            44858.24,
                            113694.36,
                            29707.92,
                            28072.36,
                            55511.08,
                            64106.76,
                            33644.92,
                            44783.84
                        ],
                        "upper": [
                            40517.12,
                            102691.68000000001,
                            26832.960000000003,
                            25355.680000000004,
                            50139.04000000001,
                            57902.880000000005,
                            30388.960000000003,
                            40449.920000000006
                        ],
                        "nominal": [
                            36176.0,
                            91689.0,
                            23958.0,
                            22639.0,
                            44767.0,
                            51699.0,
                            27133.0,
                            36116.0
                        ],
                        "lower": [
                            31834.88,
                            80686.32,
                            21083.04,
                            19922.32,
                            39394.96,
                            45495.12,
                            23877.04,
                            31782.08
                        ],
                        "lower_err": [
                            27493.760000000002,
                            69683.64,
                            18208.08,
                            17205.64,
                            34022.92,
                            39291.24,
                            20621.08,
                            27448.16
                        ]
                    }
                },
                "8": {
                    "B": {
                        "upper_err": [
                            16873.92,
                            7697.92,
                            18776.079999999998,
                            24699.56,
                            55529.68
                        ],
                        "upper": [
                            15240.960000000001,
                            6952.960000000001,
                            16959.04,
                            22309.280000000002,
                            50155.840000000004
                        ],
                        "nominal": [
                            13608.0,
                            6208.0,
                            15142.0,
                            19919.0,
                            44782.0
                        ],
                        "lower": [
                            11975.04,
                            5463.04,
                            13324.960000000001,
                            17528.72,
                            39408.16
                        ],
                        "lower_err": [
                            10342.08,
                            4718.08,
                            11507.92,
                            15138.44,
                            34034.32
                        ]
                    },
                    "R": {
                        "upper_err": [
                            29412.8,
                            33291.52,
                            63984.0,
                            35888.08,
                            30215.079999999998,
                            31084.32,
                            121079.8,
                            54940.68
                        ],
                        "upper": [
                            26566.4,
                            30069.760000000002,
                            57792.00000000001,
                            32415.040000000005,
                            27291.04,
                            28076.160000000003,
                            109362.40000000001,
                            49623.840000000004
                        ],
                        "nominal": [
                            23720.0,
                            26848.0,
                            51600.0,
                            28942.0,
                            24367.0,
                            25068.0,
                            97645.0,
                            44307.0
                        ],
                        "lower": [
                            20873.6,
                            23626.24,
                            45408.0,
                            25468.96,
                            21442.96,
                            22059.84,
                            85927.6,
                            38990.16
                        ],
                        "lower_err": [
                            18027.2,
                            20404.48,
                            39216.0,
                            21995.920000000002,
                            18518.920000000002,
                            19051.68,
                            74210.2,
                            33673.32
                        ]
                    },
                    "Z": {
                        "upper_err": [
                            44503.6,
                            128743.0,
                            35755.4,
                            34031.8,
                            66831.04,
                            75839.64,
                            40114.0,
                            52702.48
                        ],
                        "upper": [
                            40196.8,
                            116284.00000000001,
                            32295.200000000004,
                            30738.4,
                            60363.520000000004,
                            68500.32,
                            36232.0,
                            47602.240000000005
                        ],
                        "nominal": [
                            35890.0,
                            103825.0,
                            28835.0,
                            27445.0,
                            53896.0,
                            61161.0,
                            32350.0,
                            42502.0
                        ],
                        "lower": [
                            31583.2,
                            91366.0,
                            25374.8,
                            24151.6,
                            47428.48,
                            53821.68,
                            28468.0,
                            37401.76
                        ],
                        "lower_err": [
                            27276.4,
                            78907.0,
                            21914.6,
                            20858.2,
                            40960.96,
                            46482.36,
                            24586.0,
                            32301.52
                        ]
                    }
                },
                "9": {
                    "B": {
                        "upper_err": [
                            16349.4,
                            7542.92,
                            18276.36,
                            24093.2,
                            56551.44
                        ],
                        "upper": [
                            14767.2,
                            6812.960000000001,
                            16507.68,
                            21761.600000000002,
                            51078.72000000001
                        ],
                        "nominal": [
                            13185.0,
                            6083.0,
                            14739.0,
                            19430.0,
                            45606.0
                        ],
                        "lower": [
                            11602.8,
                            5353.04,
                            12970.32,
                            17098.4,
                            40133.28
                        ],
                        "lower_err": [
                            10020.6,
                            4623.08,
                            11201.64,
                            14766.8,
                            34660.56
                        ]
                    },
                    "R": {
                        "upper_err": [
                            28241.0,
                            31920.079999999998,
                            61047.68,
                            34365.36,
                            28994.92,
                            28999.88,
                            112758.16,
                            50635.4
                        ],
                        "upper": [
                            25508.000000000004,
                            28831.040000000005,
                            55139.840000000004,
                            31039.680000000004,
                            26188.960000000003,
                            26193.440000000002,
                            101846.08000000002,
                            45735.200000000004
                        ],
                        "nominal": [
                            22775.0,
                            25742.0,
                            49232.0,
                            27714.0,
                            23383.0,
                            23387.0,
                            90934.0,
                            40835.0
                        ],
                        "lower": [
                            20042.0,
                            22652.96,
                            43324.16,
                            24388.32,
                            20577.04,
                            20580.56,
                            80021.92,
                            35934.8
                        ],
                        "lower_err": [
                            17309.0,
                            19563.920000000002,
                            37416.32,
                            21062.64,
                            17771.08,
                            17774.12,
                            69109.84,
                            31034.6
                        ]
                    },
                    "Z": {
                        "upper_err": [
                            50206.36,
                            107835.36,
                            31343.48,
                            30057.6,
                            59347.64,
                            72345.31999999999,
                            37993.6,
                            51024.76
                        ],
                        "upper": [
                            45347.68000000001,
                            97399.68000000001,
                            28310.24,
                            27148.800000000003,
                            53604.32000000001,
                            65344.16,
                            34316.8,
                            46086.880000000005
                        ],
                        "nominal": [
                            40489.0,
                            86964.0,
                            25277.0,
                            24240.0,
                            47861.0,
                            58343.0,
                            30640.0,
                            41149.0
                        ],
                        "lower": [
                            35630.32,
                            76528.32,
                            22243.76,
                            21331.2,
                            42117.68,
                            51341.840000000004,
                            26963.2,
                            36211.12
                        ],
                        "lower_err": [
                            30771.64,
                            66092.64,
                            19210.52,
                            18422.4,
                            36374.36,
                            44340.68,
                            23286.4,
                            31273.24
                        ]
                    }
                }
            },
            "inputs": {
                "comment": "(night,expid) used to compute arc lamp lines",
                "nightexpids": [
                    [
                        20231210,
                        208896
                    ],
                    [
                        20231210,
                        208897
                    ],
                    [
                        20231210,
                        208898
                    ],
                    [
                        20231210,
                        208899
                    ],
                    [
                        20231210,
                        208900
                    ]
                ]
            }
        }
    },
    "CALIB long Arcs Cd+Xe": {
        "wavelength": {
            "B": [
                3612.0,
                4679.0,
                4801.0,
                5087.0
            ],
            "R": [
                6440.0
            ],
            "Z": [
                8234.0,
                8283.0,
                8822.0,
                8955.0,
                9048.0,
                9165.0,
                9802.0
            ]
        },
        "area": {
            "spectrograph": {
                "settings": {
                    "fiberlo": 240,
                    "fiberhi": 260,
                    "npix": 12,
                    "comment": "Fiber range used in spectrum; number of pixels used around line center."
                },
                "0": {
                    "B": {
                        "upper_err": [
                            10797.920000000002,
                            39061.12,
                            94231.20000000001,
                            124257.28000000001
                        ],
                        "upper": [
                            10219.460000000001,
                            36968.560000000005,
                            89183.1,
                            117600.64
                        ],
                        "nominal": [
                            9641.0,
                            34876.0,
                            84135.0,
                            110944.0
                        ],
                        "lower": [
                            9062.539999999999,
                            32783.439999999995,
                            79086.9,
                            104287.36
                        ],
                        "lower_err": [
                            8484.08,
                            30690.88,
                            74038.8,
                            97630.72
                        ]
                    },
                    "R": {
                        "upper_err": [
                            58138.08000000001
                        ],
                        "upper": [
                            55023.54
                        ],
                        "nominal": [
                            51909.0
                        ],
                        "lower": [
                            48794.46
                        ],
                        "lower_err": [
                            45679.92
                        ]
                    },
                    "Z": {
                        "upper_err": [
                            72161.6,
                            33948.32,
                            192078.88,
                            33019.840000000004,
                            49157.920000000006,
                            65729.44,
                            71626.24
                        ],
                        "upper": [
                            68295.8,
                            32129.66,
                            181788.94,
                            31250.920000000002,
                            46524.46,
                            62208.22,
                            67789.12000000001
                        ],
                        "nominal": [
                            64430.0,
                            30311.0,
                            171499.0,
                            29482.0,
                            43891.0,
                            58687.0,
                            63952.0
                        ],
                        "lower": [
                            60564.2,
                            28492.34,
                            161209.06,
                            27713.079999999998,
                            41257.54,
                            55165.78,
                            60114.88
                        ],
                        "lower_err": [
                            56698.4,
                            26673.68,
                            150919.12,
                            25944.16,
                            38624.08,
                            51644.56,
                            56277.76
                        ]
                    }
                },
                "1": {
                    "B": {
                        "upper_err": [
                            13727.840000000002,
                            42377.44,
                            104557.6,
                            144799.2
                        ],
                        "upper": [
                            12992.42,
                            40107.22,
                            98956.3,
                            137042.1
                        ],
                        "nominal": [
                            12257.0,
                            37837.0,
                            93355.0,
                            129285.0
                        ],
                        "lower": [
                            11521.58,
                            35566.78,
                            87753.7,
                            121527.9
                        ],
                        "lower_err": [
                            10786.16,
                            33296.56,
                            82152.4,
                            113770.8
                        ]
                    },
                    "R": {
                        "upper_err": [
                            59879.68000000001
                        ],
                        "upper": [
                            56671.840000000004
                        ],
                        "nominal": [
                            53464.0
                        ],
                        "lower": [
                            50256.159999999996
                        ],
                        "lower_err": [
                            47048.32
                        ]
                    },
                    "Z": {
                        "upper_err": [
                            76548.64000000001,
                            36039.36,
                            201162.08000000002,
                            34690.880000000005,
                            51382.240000000005,
                            69434.40000000001,
                            76724.48000000001
                        ],
                        "upper": [
                            72447.82,
                            34108.68,
                            190385.54,
                            32832.44,
                            48629.62,
                            65714.7,
                            72614.24
                        ],
                        "nominal": [
                            68347.0,
                            32178.0,
                            179609.0,
                            30974.0,
                            45877.0,
                            61995.0,
                            68504.0
                        ],
                        "lower": [
                            64246.17999999999,
                            30247.32,
                            168832.46,
                            29115.559999999998,
                            43124.38,
                            58275.299999999996,
                            64393.759999999995
                        ],
                        "lower_err": [
                            60145.36,
                            28316.64,
                            158055.92,
                            27257.12,
                            40371.76,
                            54555.6,
                            60283.52
                        ]
                    }
                },
                "2": {
                    "B": {
                        "upper_err": [
                            14026.880000000001,
                            43966.72,
                            107430.40000000001,
                            148895.04
                        ],
                        "upper": [
                            13275.44,
                            41611.36,
                            101675.20000000001,
                            140918.52000000002
                        ],
                        "nominal": [
                            12524.0,
                            39256.0,
                            95920.0,
                            132942.0
                        ],
                        "lower": [
                            11772.56,
                            36900.64,
                            90164.79999999999,
                            124965.48
                        ],
                        "lower_err": [
                            11021.12,
                            34545.28,
                            84409.6,
                            116988.96
                        ]
                    },
                    "R": {
                        "upper_err": [
                            55610.240000000005
                        ],
                        "upper": [
                            52631.12
                        ],
                        "nominal": [
                            49652.0
                        ],
                        "lower": [
                            46672.88
                        ],
                        "lower_err": [
                            43693.76
                        ]
                    },
                    "Z": {
                        "upper_err": [
                            77118.72,
                            35994.560000000005,
                            205540.16000000003,
                            35131.04,
                            51954.560000000005,
                            69832.0,
                            75928.16
                        ],
                        "upper": [
                            72987.36,
                            34066.28,
                            194529.08000000002,
                            33249.020000000004,
                            49171.28,
                            66091.0,
                            71860.58
                        ],
                        "nominal": [
                            68856.0,
                            32138.0,
                            183518.0,
                            31367.0,
                            46388.0,
                            62350.0,
                            67793.0
                        ],
                        "lower": [
                            64724.64,
                            30209.719999999998,
                            172506.91999999998,
                            29484.98,
                            43604.72,
                            58609.0,
                            63725.42
                        ],
                        "lower_err": [
                            60593.28,
                            28281.44,
                            161495.84,
                            27602.96,
                            40821.44,
                            54868.0,
                            59657.840000000004
                        ]
                    }
                },
                "3": {
                    "B": {
                        "upper_err": [
                            8970.080000000002,
                            43974.560000000005,
                            108477.6,
                            151273.92
                        ],
                        "upper": [
                            8489.54,
                            41618.78,
                            102666.3,
                            143169.96000000002
                        ],
                        "nominal": [
                            8009.0,
                            39263.0,
                            96855.0,
                            135066.0
                        ],
                        "lower": [
                            7528.459999999999,
                            36907.22,
                            91043.7,
                            126962.04
                        ],
                        "lower_err": [
                            7047.92,
                            34551.44,
                            85232.4,
                            118858.08
                        ]
                    },
                    "R": {
                        "upper_err": [
                            53471.04000000001
                        ],
                        "upper": [
                            50606.520000000004
                        ],
                        "nominal": [
                            47742.0
                        ],
                        "lower": [
                            44877.479999999996
                        ],
                        "lower_err": [
                            42012.96
                        ]
                    },
                    "Z": {
                        "upper_err": [
                            78529.92000000001,
                            36816.64000000001,
                            211126.72000000003,
                            36624.0,
                            54658.240000000005,
                            73326.40000000001,
                            80128.16
                        ],
                        "upper": [
                            74322.96,
                            34844.32,
                            199816.36000000002,
                            34662.0,
                            51730.12,
                            69398.2,
                            75835.58
                        ],
                        "nominal": [
                            70116.0,
                            32872.0,
                            188506.0,
                            32700.0,
                            48802.0,
                            65470.0,
                            71543.0
                        ],
                        "lower": [
                            65909.04,
                            30899.679999999997,
                            177195.63999999998,
                            30738.0,
                            45873.88,
                            61541.799999999996,
                            67250.42
                        ],
                        "lower_err": [
                            61702.08,
                            28927.36,
                            165885.28,
                            28776.0,
                            42945.76,
                            57613.6,
                            62957.840000000004
                        ]
                    }
                },
                "4": {
                    "B": {
                        "upper_err": [
                            8184.960000000001,
                            48437.76,
                            119356.16000000002,
                            162859.2
                        ],
                        "upper": [
                            7746.4800000000005,
                            45842.880000000005,
                            112962.08,
                            154134.6
                        ],
                        "nominal": [
                            7308.0,
                            43248.0,
                            106568.0,
                            145410.0
                        ],
                        "lower": [
                            6869.5199999999995,
                            40653.119999999995,
                            100173.92,
                            136685.4
                        ],
                        "lower_err": [
                            6431.04,
                            38058.24,
                            93779.84,
                            127960.8
                        ]
                    },
                    "R": {
                        "upper_err": [
                            57401.12
                        ],
                        "upper": [
                            54326.060000000005
                        ],
                        "nominal": [
                            51251.0
                        ],
                        "lower": [
                            48175.939999999995
                        ],
                        "lower_err": [
                            45100.88
                        ]
                    },
                    "Z": {
                        "upper_err": [
                            76348.16,
                            36014.72,
                            205427.04,
                            35021.280000000006,
                            52356.64000000001,
                            68841.92000000001,
                            78143.52
                        ],
                        "upper": [
                            72258.08,
                            34085.36,
                            194422.02000000002,
                            33145.14,
                            49551.82,
                            65153.96000000001,
                            73957.26000000001
                        ],
                        "nominal": [
                            68168.0,
                            32156.0,
                            183417.0,
                            31269.0,
                            46747.0,
                            61466.0,
                            69771.0
                        ],
                        "lower": [
                            64077.92,
                            30226.64,
                            172411.97999999998,
                            29392.859999999997,
                            43942.18,
                            57778.03999999999,
                            65584.73999999999
                        ],
                        "lower_err": [
                            59987.840000000004,
                            28297.28,
                            161406.96,
                            27516.72,
                            41137.36,
                            54090.08,
                            61398.48
                        ]
                    }
                },
                "5": {
                    "B": {
                        "upper_err": [
                            10908.800000000001,
                            40249.44,
                            98924.00000000001,
                            138996.48
                        ],
                        "upper": [
                            10324.4,
                            38093.22,
                            93624.5,
                            131550.24000000002
                        ],
                        "nominal": [
                            9740.0,
                            35937.0,
                            88325.0,
                            124104.0
                        ],
                        "lower": [
                            9155.6,
                            33780.78,
                            83025.5,
                            116657.76
                        ],
                        "lower_err": [
                            8571.2,
                            31624.56,
                            77726.0,
                            109211.52
                        ]
                    },
                    "R": {
                        "upper_err": [
                            50685.600000000006
                        ],
                        "upper": [
                            47970.3
                        ],
                        "nominal": [
                            45255.0
                        ],
                        "lower": [
                            42539.7
                        ],
                        "lower_err": [
                            39824.4
                        ]
                    },
                    "Z": {
                        "upper_err": [
                            69650.56000000001,
                            33864.32,
                            199020.64,
                            34135.36,
                            51306.08,
                            70832.16,
                            98660.8
                        ],
                        "upper": [
                            65919.28,
                            32050.16,
                            188358.82,
                            32306.68,
                            48557.54,
                            67037.58,
                            93375.40000000001
                        ],
                        "nominal": [
                            62188.0,
                            30236.0,
                            177697.0,
                            30478.0,
                            45809.0,
                            63243.0,
                            88090.0
                        ],
                        "lower": [
                            58456.719999999994,
                            28421.84,
                            167035.18,
                            28649.32,
                            43060.46,
                            59448.42,
                            82804.59999999999
                        ],
                        "lower_err": [
                            54725.44,
                            26607.68,
                            156373.36000000002,
                            26820.64,
                            40311.92,
                            55653.840000000004,
                            77519.2
                        ]
                    }
                },
                "6": {
                    "B": {
                        "upper_err": [
                            11215.68,
                            40920.32000000001,
                            100636.48000000001,
                            135166.08000000002
                        ],
                        "upper": [
                            10614.84,
                            38728.16,
                            95245.24,
                            127925.04000000001
                        ],
                        "nominal": [
                            10014.0,
                            36536.0,
                            89854.0,
                            120684.0
                        ],
                        "lower": [
                            9413.16,
                            34343.84,
                            84462.76,
                            113442.95999999999
                        ],
                        "lower_err": [
                            8812.32,
                            32151.68,
                            79071.52,
                            106201.92
                        ]
                    },
                    "R": {
                        "upper_err": [
                            53872.00000000001
                        ],
                        "upper": [
                            50986.0
                        ],
                        "nominal": [
                            48100.0
                        ],
                        "lower": [
                            45214.0
                        ],
                        "lower_err": [
                            42328.0
                        ]
                    },
                    "Z": {
                        "upper_err": [
                            65558.08,
                            30927.680000000004,
                            176296.96000000002,
                            30390.08,
                            44789.920000000006,
                            61013.12,
                            67556.16
                        ],
                        "upper": [
                            62046.04,
                            29270.84,
                            166852.48,
                            28762.04,
                            42390.46,
                            57744.560000000005,
                            63937.08
                        ],
                        "nominal": [
                            58534.0,
                            27614.0,
                            157408.0,
                            27134.0,
                            39991.0,
                            54476.0,
                            60318.0
                        ],
                        "lower": [
                            55021.96,
                            25957.16,
                            147963.52,
                            25505.96,
                            37591.54,
                            51207.439999999995,
                            56698.92
                        ],
                        "lower_err": [
                            51509.92,
                            24300.32,
                            138519.04,
                            23877.920000000002,
                            35192.08,
                            47938.88,
                            53079.840000000004
                        ]
                    }
                },
                "7": {
                    "B": {
                        "upper_err": [
                            11112.640000000001,
                            42590.240000000005,
                            104070.40000000001,
                            143906.56000000003
                        ],
                        "upper": [
                            10517.32,
                            40308.62,
                            98495.20000000001,
                            136197.28
                        ],
                        "nominal": [
                            9922.0,
                            38027.0,
                            92920.0,
                            128488.0
                        ],
                        "lower": [
                            9326.68,
                            35745.38,
                            87344.79999999999,
                            120778.71999999999
                        ],
                        "lower_err": [
                            8731.36,
                            33463.76,
                            81769.6,
                            113069.44
                        ]
                    },
                    "R": {
                        "upper_err": [
                            51474.08
                        ],
                        "upper": [
                            48716.54
                        ],
                        "nominal": [
                            45959.0
                        ],
                        "lower": [
                            43201.46
                        ],
                        "lower_err": [
                            40443.92
                        ]
                    },
                    "Z": {
                        "upper_err": [
                            62819.68000000001,
                            29591.520000000004,
                            169130.08000000002,
                            29159.200000000004,
                            43498.560000000005,
                            58525.600000000006,
                            58474.08000000001
                        ],
                        "upper": [
                            59454.340000000004,
                            28006.260000000002,
                            160069.54,
                            27597.100000000002,
                            41168.28,
                            55390.3,
                            55341.54
                        ],
                        "nominal": [
                            56089.0,
                            26421.0,
                            151009.0,
                            26035.0,
                            38838.0,
                            52255.0,
                            52209.0
                        ],
                        "lower": [
                            52723.659999999996,
                            24835.739999999998,
                            141948.46,
                            24472.899999999998,
                            36507.72,
                            49119.7,
                            49076.46
                        ],
                        "lower_err": [
                            49358.32,
                            23250.48,
                            132887.92,
                            22910.8,
                            34177.44,
                            45984.4,
                            45943.92
                        ]
                    }
                },
                "8": {
                    "B": {
                        "upper_err": [
                            9776.480000000001,
                            39782.4,
                            95036.48000000001,
                            124850.88
                        ],
                        "upper": [
                            9252.74,
                            37651.200000000004,
                            89945.24,
                            118162.44
                        ],
                        "nominal": [
                            8729.0,
                            35520.0,
                            84854.0,
                            111474.0
                        ],
                        "lower": [
                            8205.26,
                            33388.799999999996,
                            79762.76,
                            104785.56
                        ],
                        "lower_err": [
                            7681.52,
                            31257.6,
                            74671.52,
                            98097.12
                        ]
                    },
                    "R": {
                        "upper_err": [
                            55100.64000000001
                        ],
                        "upper": [
                            52148.82
                        ],
                        "nominal": [
                            49197.0
                        ],
                        "lower": [
                            46245.18
                        ],
                        "lower_err": [
                            43293.36
                        ]
                    },
                    "Z": {
                        "upper_err": [
                            75704.16,
                            35509.600000000006,
                            198869.44000000003,
                            34286.560000000005,
                            50776.32000000001,
                            67735.36,
                            71765.12000000001
                        ],
                        "upper": [
                            71648.58,
                            33607.3,
                            188215.72,
                            32449.780000000002,
                            48056.16,
                            64106.68,
                            67920.56
                        ],
                        "nominal": [
                            67593.0,
                            31705.0,
                            177562.0,
                            30613.0,
                            45336.0,
                            60478.0,
                            64076.0
                        ],
                        "lower": [
                            63537.42,
                            29802.699999999997,
                            166908.28,
                            28776.219999999998,
                            42615.84,
                            56849.32,
                            60231.439999999995
                        ],
                        "lower_err": [
                            59481.840000000004,
                            27900.4,
                            156254.56,
                            26939.44,
                            39895.68,
                            53220.64,
                            56386.88
                        ]
                    }
                },
                "9": {
                    "B": {
                        "upper_err": [
                            7183.68,
                            39079.04,
                            92962.24,
                            121770.88
                        ],
                        "upper": [
                            6798.84,
                            36985.520000000004,
                            87982.12000000001,
                            115247.44
                        ],
                        "nominal": [
                            6414.0,
                            34892.0,
                            83002.0,
                            108724.0
                        ],
                        "lower": [
                            6029.16,
                            32798.479999999996,
                            78021.87999999999,
                            102200.56
                        ],
                        "lower_err": [
                            5644.32,
                            30704.96,
                            73041.76,
                            95677.12
                        ]
                    },
                    "R": {
                        "upper_err": [
                            51924.32000000001
                        ],
                        "upper": [
                            49142.66
                        ],
                        "nominal": [
                            46361.0
                        ],
                        "lower": [
                            43579.34
                        ],
                        "lower_err": [
                            40797.68
                        ]
                    },
                    "Z": {
                        "upper_err": [
                            65819.04000000001,
                            31309.600000000002,
                            190025.92,
                            33238.240000000005,
                            49619.36000000001,
                            67775.68000000001,
                            77931.84000000001
                        ],
                        "upper": [
                            62293.020000000004,
                            29632.300000000003,
                            179845.96000000002,
                            31457.620000000003,
                            46961.18,
                            64144.840000000004,
                            73756.92
                        ],
                        "nominal": [
                            58767.0,
                            27955.0,
                            169666.0,
                            29677.0,
                            44303.0,
                            60514.0,
                            69582.0
                        ],
                        "lower": [
                            55240.979999999996,
                            26277.699999999997,
                            159486.03999999998,
                            27896.379999999997,
                            41644.82,
                            56883.159999999996,
                            65407.079999999994
                        ],
                        "lower_err": [
                            51714.96,
                            24600.4,
                            149306.08,
                            26115.76,
                            38986.64,
                            53252.32,
                            61232.16
                        ]
                    }
                }
            },
            "inputs": {
                "comment": "(night,expid) used to compute arc lamp lines",
                "nightexpids": [
                    [
                        20231210,
                        208903
                    ],
                    [
                        20231210,
                        208904
                    ],
                    [
                        20231210,
                        208905
                    ],
                    [
                        20231210,
                        208906
                    ],
                    [
                        20231210,
                        208907
                    ]
                ]
            }
        }
    }
}